{"sections":{"main":{"type":"main-page","disabled":true,"settings":{"color_scheme":"","heading_text_align":"text-align-left","sm_size_multiplier":"sm-size--default","md_padding_top":40,"md_padding_bottom":40,"size_multiplier":"size--default","padding_top":80,"padding_bottom":80}},"contact_form":{"type":"contact-form","blocks":{"template--16212602060989__3a48de0d-8d7b-4d18-8fac-44c00f552f27-title-1":{"type":"title","settings":{"title":"CONTACT FORM","heading_tag":"h1","sm_size_multiplier":"sm-size--default","sm_margin_top":0,"sm_margin_bottom":0,"size_multiplier":"size--default","margin_top":0,"margin_bottom":0}},"template--16212602060989__3a48de0d-8d7b-4d18-8fac-44c00f552f27-text-1":{"type":"text","settings":{"text":"<p>We’re here to answer any questions you have regarding<br\/>BRAiNLUBE!<\/p>","sm_size_multiplier":"sm-size--default","sm_margin_top":0,"sm_margin_bottom":0,"size_multiplier":"size--default","margin_top":0,"margin_bottom":0}},"template--16212602060989__3a48de0d-8d7b-4d18-8fac-44c00f552f27-input-1":{"type":"input","settings":{"label":"Name","type":"text","width":"half-width","required":true}},"template--16212602060989__3a48de0d-8d7b-4d18-8fac-44c00f552f27-email-1":{"type":"email","settings":{"label":"Email","width":"half-width"}},"template--16212602060989__3a48de0d-8d7b-4d18-8fac-44c00f552f27-input-2":{"type":"input","settings":{"label":"Phone","type":"tel","width":"full-width","required":false}},"template--16212602060989__3a48de0d-8d7b-4d18-8fac-44c00f552f27-input-3":{"type":"input","settings":{"label":"Subject","type":"text","width":"full-width","required":false}},"template--16212602060989__3a48de0d-8d7b-4d18-8fac-44c00f552f27-input-4":{"type":"input","settings":{"label":"Message","type":"textarea","width":"full-width","required":true}}},"block_order":["template--16212602060989__3a48de0d-8d7b-4d18-8fac-44c00f552f27-title-1","template--16212602060989__3a48de0d-8d7b-4d18-8fac-44c00f552f27-text-1","template--16212602060989__3a48de0d-8d7b-4d18-8fac-44c00f552f27-input-1","template--16212602060989__3a48de0d-8d7b-4d18-8fac-44c00f552f27-email-1","template--16212602060989__3a48de0d-8d7b-4d18-8fac-44c00f552f27-input-2","template--16212602060989__3a48de0d-8d7b-4d18-8fac-44c00f552f27-input-3","template--16212602060989__3a48de0d-8d7b-4d18-8fac-44c00f552f27-input-4"],"custom_css":["h1 {font-weight: bold;}"],"settings":{"color_scheme":"alternative-1","text_align":"text-align-left","md_padding_top":104,"md_padding_bottom":104,"padding_top":80,"padding_bottom":80}},"featured_article_8k46pg":{"type":"featured-article","blocks":{"image_XN8KDN":{"type":"image","settings":{"media_aspect_ratio":"natural"}},"article_title_yLpfdY":{"type":"article_title","settings":{"heading_tag":"h2","sm_size_multiplier":"sm-size--default","sm_margin_top":0,"size_multiplier":"size--default","margin_top":0}},"details_gqzbTc":{"type":"details","settings":{"show_author":true,"show_date":true,"sm_margin_top":20,"margin_top":20}},"article_body_qMTxir":{"type":"article_body","settings":{"sm_size_multiplier":"sm-size--default","sm_margin_top":20,"size_multiplier":"size--default","margin_top":20}},"button_HawEGp":{"type":"button","settings":{"button_label":"Read more","button_style":"","sm_size_multiplier":"sm-size--default","sm_margin_top":24,"size_multiplier":"size--default","margin_top":24}}},"block_order":["image_XN8KDN","article_title_yLpfdY","details_gqzbTc","article_body_qMTxir","button_HawEGp"],"name":"t:sections.featured-article.name","settings":{"article":"brainwaves\/the-brainlube-story","color_scheme":"default","enable_full_width":false,"media_position":"media_first","content_width":"col-sm-max-4","desktop_alignment":"sm-text-align-left","sm_full_width_buttons":false,"md_padding_top":40,"md_padding_bottom":40,"mobile_alignment":"text-align-left","full_width_buttons":false,"padding_top":0,"padding_bottom":24}},"divider_fCAmYp":{"type":"divider","blocks":{"standard_3gHQ3y":{"type":"standard","settings":{"divider_graphics":"waves","top_part_color":"#c7e8e5","middle_part_color":"linear-gradient(284deg, rgba(255, 255, 255, 1), rgba(255, 255, 255, 1) 95.324%)","bottom_part_color":"#006eb9","position":"top-previous","flip_horizontal":false,"flip_vertical":false,"sm_graphics_height":100,"sm_graphics_width":100,"graphics_height":0,"graphics_width":100}}},"block_order":["standard_3gHQ3y"],"name":"t:sections.divider.name","settings":{"md_padding_top":96,"md_padding_bottom":0,"padding_top":80,"padding_bottom":0}}},"order":["main","contact_form","featured_article_8k46pg","divider_fCAmYp"]}